algopack/__init__.py
algopack/sort.cpython-36m-darwin.so
algopack/stack.cpython-36m-darwin.so
algopack-0.0.4.dist-info/LICENSE.txt
algopack-0.0.4.dist-info/METADATA
algopack-0.0.4.dist-info/WHEEL
algopack-0.0.4.dist-info/top_level.txt
algopack-0.0.4.dist-info/RECORD
