Metadata-Version: 2.1
Name: algopack
Version: 0.0.4
Summary: Implementation of various common CS algortihms in Cython
Home-page: https://github.com/divykj/algopack
Author: Divya Jain
Author-email: dkj@somaiya.edu
License: MIT
Project-URL: Documentation, https://github.com/divykj/algopack
Project-URL: Code, https://github.com/divykj/algopack
Project-URL: Issue tracker, https://github.com/divykj/algopack/issues
Platform: UNKNOWN
Classifier: Development Status :: 3 - Alpha
Classifier: License :: OSI Approved :: MIT License
Classifier: Intended Audience :: Education
Classifier: Intended Audience :: Science/Research
Classifier: Topic :: Education
Classifier: Topic :: Scientific/Engineering
Classifier: Topic :: Scientific/Engineering :: Mathematics
Classifier: Natural Language :: English
Classifier: Operating System :: OS Independent
Classifier: Programming Language :: C
Classifier: Programming Language :: Cython
Classifier: Programming Language :: Python
Classifier: Programming Language :: Python :: 3
Classifier: Programming Language :: Python :: 3.6
Classifier: Programming Language :: Python :: 3.7
Classifier: Programming Language :: Python :: 3.8
Classifier: Programming Language :: Python :: 3 :: Only
Classifier: Programming Language :: Python :: Implementation :: CPython
Requires-Python: >=3.6
Provides-Extra: dev
